weni/activities/__init__.py
weni/activities/apps.py
weni/activities/migrations/__init__.py
weni/activities/recent_activities.py
weni/activities/signals.py
weni/analytics_api/README.md
weni/analytics_api/__init__.py
weni/analytics_api/apps.py
weni/analytics_api/tests.py
weni/analytics_api/urls.py
weni/analytics_api/views.py
weni/auth/__init__.py
weni/auth/apps.py
weni/auth/backends.py
weni/auth/decorators.py
weni/auth/urls.py
weni/auth/views.py
weni/channel_stats/README.md
weni/channel_stats/__init__.py
weni/channel_stats/apps.py
weni/channel_stats/serializers.py
weni/channel_stats/urls.py
weni/channel_stats/views.py
weni/grpc/billing/__init__.py
weni/grpc/billing/apps.py
weni/grpc/billing/queries.py
weni/grpc/billing/serializers.py
weni/grpc/billing/services.py
weni/grpc/billing/tests.py
weni/grpc/billing/urls.py
weni/grpc/channel/__init__.py
weni/grpc/channel/apps.py
weni/grpc/channel/fields.py
weni/grpc/channel/serializers.py
weni/grpc/channel/services.py
weni/grpc/channel/tests.py
weni/grpc/channel/urls.py
weni/grpc/classifier/__init__.py
weni/grpc/classifier/apps.py
weni/grpc/classifier/serializers.py
weni/grpc/classifier/services.py
weni/grpc/classifier/tests.py
weni/grpc/classifier/urls.py
weni/grpc/core/__init__.py
weni/grpc/core/apps.py
weni/grpc/core/management/__init__.py
weni/grpc/core/management/commands/__init__.py
weni/grpc/core/management/commands/grpc.py
weni/grpc/core/serializers.py
weni/grpc/core/services.py
weni/grpc/core/tests.py
weni/grpc/core/urls.py
weni/grpc/flow/__init__.py
weni/grpc/flow/apps.py
weni/grpc/flow/serializers.py
weni/grpc/flow/services.py
weni/grpc/flow/tests.py
weni/grpc/flow/urls.py
weni/grpc/org/__init__.py
weni/grpc/org/apps.py
weni/grpc/org/serializers.py
weni/grpc/org/services.py
weni/grpc/org/tests.py
weni/grpc/org/urls.py
weni/grpc/statistic/__init__.py
weni/grpc/statistic/apps.py
weni/grpc/statistic/services.py
weni/grpc/statistic/tests.py
weni/grpc/statistic/urls.py
weni/grpc/user/__init__.py
weni/grpc/user/apps.py
weni_rp_apps-2.10.7.dist-info/METADATA
weni_rp_apps-2.10.7.dist-info/WHEEL
weni_rp_apps-2.10.7.dist-info/RECORD
