Metadata-Version: 2.3
Name: weni-rp-apps
Version: 2.10.7
Summary: Weni apps for Rapidpro Platform
License: AGPL-3.0
Author: jcbalmeida
Requires-Python: >=3.7,<4.0
Classifier: License :: OSI Approved :: GNU Affero General Public License v3
Classifier: Programming Language :: Python :: 3
Classifier: Programming Language :: Python :: 3.7
Classifier: Programming Language :: Python :: 3.8
Classifier: Programming Language :: Python :: 3.9
Classifier: Programming Language :: Python :: 3.10
Classifier: Programming Language :: Python :: 3.11
Classifier: Programming Language :: Python :: 3.12
Classifier: Programming Language :: Python :: 3.13
Requires-Dist: django-csp (>=3.7,<4.0)
Requires-Dist: django-environ (>=0.7.0,<0.8.0)
Requires-Dist: django-templates-macros (>=0.2,<0.3)
Requires-Dist: djangogrpcframework (>=0.2.1,<0.3.0)
Requires-Dist: drf-nested-routers (>=0.93.4,<0.94.0)
Requires-Dist: elastic-apm (>=6.4.0,<7.0.0)
Requires-Dist: flower (>=0.9,<0.10)
Requires-Dist: mozilla-django-oidc (>=2.0.0,<3.0.0)
Requires-Dist: pre-commit (>=2.20.0,<3.0.0)
